GameSentenceMiner/__init__.py
GameSentenceMiner/anki.py
GameSentenceMiner/gametext.py
GameSentenceMiner/gsm.py
GameSentenceMiner/obs.py
GameSentenceMiner/vad.py
GameSentenceMiner/ai/__init__.py
GameSentenceMiner/ai/ai_prompting.py
GameSentenceMiner/assets/__init__.py
GameSentenceMiner/assets/icon.png
GameSentenceMiner/assets/icon128.png
GameSentenceMiner/assets/icon256.png
GameSentenceMiner/assets/icon32.png
GameSentenceMiner/assets/icon512.png
GameSentenceMiner/assets/icon64.png
GameSentenceMiner/assets/pickaxe.png
GameSentenceMiner/locales/en_us.json
GameSentenceMiner/locales/es_es.json
GameSentenceMiner/locales/ja_jp.json
GameSentenceMiner/locales/zh_cn.json
GameSentenceMiner/mecab/LICENSE
GameSentenceMiner/mecab/README.md
GameSentenceMiner/mecab/__init__.py
GameSentenceMiner/mecab/__main__.py
GameSentenceMiner/mecab/basic_mecab_controller.py
GameSentenceMiner/mecab/basic_types.py
GameSentenceMiner/mecab/compound_furigana.py
GameSentenceMiner/mecab/format.py
GameSentenceMiner/mecab/kana_conv.py
GameSentenceMiner/mecab/lru_cache.py
GameSentenceMiner/mecab/mecab_controller.py
GameSentenceMiner/mecab/mecab_exe_finder.py
GameSentenceMiner/mecab/replace_mistakes.py
GameSentenceMiner/mecab/unify_readings.py
GameSentenceMiner/mecab/support/LICENSE
GameSentenceMiner/mecab/support/LICENSE.MECAB-IPADIC
GameSentenceMiner/mecab/support/char.bin
GameSentenceMiner/mecab/support/dicrc
GameSentenceMiner/mecab/support/itaijidict
GameSentenceMiner/mecab/support/kanwadict
GameSentenceMiner/mecab/support/libmecab.2.dylib
GameSentenceMiner/mecab/support/libmecab.dll
GameSentenceMiner/mecab/support/libmecab.so.1
GameSentenceMiner/mecab/support/matrix.bin
GameSentenceMiner/mecab/support/mecab.exe
GameSentenceMiner/mecab/support/mecab.lin
GameSentenceMiner/mecab/support/mecab.mac
GameSentenceMiner/mecab/support/mecabrc
GameSentenceMiner/mecab/support/sys.dic
GameSentenceMiner/mecab/support/unk.dic
GameSentenceMiner/mecab/support/user_dic.dic
GameSentenceMiner/ocr/__init__.py
gamesentenceminer-2.23.31.dist-info/licenses/LICENSE
gamesentenceminer-2.23.31.dist-info/METADATA
gamesentenceminer-2.23.31.dist-info/WHEEL
gamesentenceminer-2.23.31.dist-info/entry_points.txt
gamesentenceminer-2.23.31.dist-info/top_level.txt
gamesentenceminer-2.23.31.dist-info/RECORD
