Metadata-Version: 2.4
Name: GameSentenceMiner
Version: 2.23.31
Summary: A tool for mining sentences from games. Update: Dependencies, replay buffer based line searching, and bug fixes.
Author-email: Beangate <bpwhelan95@gmail.com>
License: MIT License
Project-URL: Homepage, https://github.com/bpwhelan/GameSentenceMiner
Project-URL: Repository, https://github.com/bpwhelan/GameSentenceMiner
Classifier: Programming Language :: Python :: 3
Classifier: License :: OSI Approved :: MIT License
Classifier: Operating System :: OS Independent
Requires-Python: <3.14,>=3.10
License-File: LICENSE
Requires-Dist: requests~=2.32.5
Requires-Dist: watchdog~=6.0.0
Requires-Dist: DateTime~=5.5
Requires-Dist: soundfile~=0.13.1
Requires-Dist: toml~=0.10.2
Requires-Dist: psutil~=7.1.0
Requires-Dist: rapidfuzz~=3.10.0
Requires-Dist: plyer~=2.1.0
Requires-Dist: keyboard~=0.13.5
Requires-Dist: websockets~=15.0.1
Requires-Dist: dataclasses_json~=0.6.7
Requires-Dist: obsws-python~=1.8.0
Requires-Dist: numpy==2.2.6
Requires-Dist: faster-whisper~=1.2.1
Requires-Dist: silero-vad~=6.2.0
Requires-Dist: regex~=2025.10.23
Requires-Dist: opencv-python~=4.12.0.88
Requires-Dist: scikit-image~=0.25.2
Requires-Dist: oneocr==1.0.10
Requires-Dist: google-genai~=1.46.0
Requires-Dist: sounddevice~=0.5.2
Requires-Dist: matplotlib~=3.10.6
Requires-Dist: groq~=0.33.0
Requires-Dist: flask~=3.1.2
Requires-Dist: pystray~=0.19.5
Requires-Dist: pygetwindow==0.0.9; sys_platform == "win32"
Requires-Dist: pywin32==311; sys_platform == "win32"
Requires-Dist: win10toast==0.9; sys_platform == "win32"
Requires-Dist: stable-ts~=2.19.1
Requires-Dist: torchcodec~=0.8.1
Requires-Dist: torchaudio~=2.8.0
Requires-Dist: torch~=2.8.0
Requires-Dist: pillow~=12.0.0
Requires-Dist: openai~=2.6.0
Requires-Dist: flask-compress~=1.15
Requires-Dist: meikiocr~=0.1.4
Requires-Dist: jaconv~=0.4.0
Requires-Dist: loguru~=0.7.3
Requires-Dist: pyperclipfix>=1.9.4
Requires-Dist: desktop-notifier>=6.1.0
Requires-Dist: mss>=10.1.0
Requires-Dist: pyobjc~=10.3.1; sys_platform == "darwin"
Requires-Dist: pyqt6~=6.10.0
Requires-Dist: pyqtdarktheme~=2.1.0
Requires-Dist: langid~=1.1.6
Requires-Dist: pysbd~=0.3.4
Requires-Dist: pypresence>=4.6.1
Requires-Dist: tokenizers==0.22.1
Requires-Dist: curl-cffi~=0.13.0
Requires-Dist: betterproto==2.0.0b7
Requires-Dist: py7zr~=1.0.0
Requires-Dist: waitress==3.0.2
Requires-Dist: flasgger~=0.9.7
Requires-Dist: pynput~=1.8.1; sys_platform == "win32"
Requires-Dist: uv>=0.9.22
Requires-Dist: pip>=25.3
Requires-Dist: ollama>=0.6.1
Provides-Extra: lens
Requires-Dist: betterproto==2.0.0b7; extra == "lens"
Provides-Extra: gpu
Requires-Dist: onnxruntime-gpu[cuda,cudnn]; extra == "gpu"
Dynamic: license-file
